coinstac_pyprofiler/__init__.py
coinstac_pyprofiler/custom_profile_merger.py
coinstac_pyprofiler/custom_profiler.py
coinstac_pyprofiler/visualizer.py
coinstac_pyprofiler/core/AbstractNode.py
coinstac_pyprofiler/core/InnerNode.py
coinstac_pyprofiler/core/RootNode.py
coinstac_pyprofiler/core/__init__.py
coinstac_pyprofiler/core/renderer.py
coinstac_pyprofiler/core/utils.py
coinstac_pyprofiler-0.1.0.dist-info/LICENSE
coinstac_pyprofiler-0.1.0.dist-info/METADATA
coinstac_pyprofiler-0.1.0.dist-info/WHEEL
coinstac_pyprofiler-0.1.0.dist-info/top_level.txt
coinstac_pyprofiler-0.1.0.dist-info/RECORD
