Metadata-Version: 2.1
Name: coinstac-pyprofiler
Version: 0.1.0
Summary: A wrapper for some existing python profilers
Home-page: UNKNOWN
Author: Sunitha Basodi
Author-email: sunitha.basodi@gmail.com
License: UNKNOWN
Platform: UNKNOWN
Classifier: Programming Language :: Python :: 3
Classifier: License :: OSI Approved :: MIT License
Requires-Python: >=3.6
Requires-Dist: pyinstrument (~=3.2.0)
Requires-Dist: CProfileV (~=1.0.7)
Requires-Dist: anytree (~=2.8.0)
Requires-Dist: graphviz (~=0.14.2)
